py2pd/__init__.py
py2pd/api.py
py2pd/ast.py
py2pd-0.1.1.dist-info/WHEEL
py2pd-0.1.1.dist-info/METADATA
py2pd-0.1.1.dist-info/RECORD
