Metadata-Version: 2.4
Name: py2pd
Version: 0.1.1
Summary: Roundtrip parsing and generation of pure-data patches from python
Keywords: puredata,pd,audio,dsp,music,synthesis,patching
Author: Shakeeb Alireza
Author-email: Shakeeb Alireza <shakfu@users.noreply.github.com>
License-Expression: MIT
Classifier: Development Status :: 4 - Beta
Classifier: Environment :: Console
Classifier: Intended Audience :: Developers
Classifier: Intended Audience :: End Users/Desktop
Classifier: License :: OSI Approved :: MIT License
Classifier: Operating System :: OS Independent
Classifier: Programming Language :: Python :: 3
Classifier: Programming Language :: Python :: 3.13
Classifier: Programming Language :: Python :: Implementation :: CPython
Classifier: Topic :: Multimedia :: Sound/Audio
Classifier: Topic :: Multimedia :: Sound/Audio :: Sound Synthesis
Classifier: Topic :: Software Development :: Code Generators
Classifier: Topic :: Software Development :: Libraries :: Python Modules
Classifier: Typing :: Typed
Requires-Python: >=3.13
Project-URL: Homepage, https://github.com/shakfu/py2pd
Project-URL: Repository, https://github.com/shakfu/py2pd
Project-URL: Issues, https://github.com/shakfu/py2pd/issues
Project-URL: Changelog, https://github.com/shakfu/py2pd/blob/main/CHANGELOG.md
